CHANGES.rst
CONTRIBUTORS.rst
LICENSE.GPL
LICENSE.rst
MANIFEST.in
README.rst
requirements.txt
setup.cfg
setup.py
docs/index.rst
src/collective/__init__.py
src/collective.sortedlisting.egg-info/PKG-INFO
src/collective.sortedlisting.egg-info/SOURCES.txt
src/collective.sortedlisting.egg-info/dependency_links.txt
src/collective.sortedlisting.egg-info/entry_points.txt
src/collective.sortedlisting.egg-info/namespace_packages.txt
src/collective.sortedlisting.egg-info/not-zip-safe
src/collective.sortedlisting.egg-info/requires.txt
src/collective.sortedlisting.egg-info/top_level.txt
src/collective/sortedlisting/__init__.py
src/collective/sortedlisting/behavior.py
src/collective/sortedlisting/configure.zcml
src/collective/sortedlisting/content.py
src/collective/sortedlisting/interfaces.py
src/collective/sortedlisting/setuphandlers.py
src/collective/sortedlisting/testing.py
src/collective/sortedlisting/tile.py
src/collective/sortedlisting/widget.py
src/collective/sortedlisting/browser/__init__.py
src/collective/sortedlisting/browser/collection.py
src/collective/sortedlisting/browser/configure.zcml
src/collective/sortedlisting/browser/querybuilder.py
src/collective/sortedlisting/browser/results.pt
src/collective/sortedlisting/browser/static/bundle-sortablequerystring-compiled.js
src/collective/sortedlisting/browser/static/bundle.js
src/collective/sortedlisting/browser/static/sortablequerystring-compiled.css
src/collective/sortedlisting/browser/static/sortablequerystring-compiled.css.map
src/collective/sortedlisting/browser/static/sortablequerystring-compiled.min.js
src/collective/sortedlisting/browser/static/sortablequerystring-compiled.min.js.map
src/collective/sortedlisting/browser/static/sortablequerystring/pattern.js
src/collective/sortedlisting/browser/static/sortablequerystring/pattern.less
src/collective/sortedlisting/locales/collective.sortedlisting.pot
src/collective/sortedlisting/locales/update.sh
src/collective/sortedlisting/profiles/default/browserlayer.xml
src/collective/sortedlisting/profiles/default/metadata.xml
src/collective/sortedlisting/profiles/default/registry.xml
src/collective/sortedlisting/profiles/default/types.xml
src/collective/sortedlisting/profiles/default/types/SortableCollection.xml
src/collective/sortedlisting/profiles/mosaic/registry.xml
src/collective/sortedlisting/profiles/uninstall/browserlayer.xml
src/collective/sortedlisting/schema/__init__.py
