Metadata-Version: 1.1
Name: collective.sortedlisting
Version: 1.0a1
Summary: Sorted listings in Plone
Home-page: https://pypi.python.org/pypi/collective.sortedlisting
Author: Tom Gross
Author-email: itconsense@gmail.com
License: GPL version 2
Keywords: Python Plone
Platform: UNKNOWN
Classifier: Environment :: Web Environment
Classifier: Framework :: Plone
Classifier: Framework :: Plone :: 5.1
Classifier: Programming Language :: Python
Classifier: Programming Language :: Python :: 2.7
Classifier: Operating System :: OS Independent
Classifier: License :: OSI Approved :: GNU General Public License v2 (GPLv2)
